keycloak_api_client/__init__.py
keycloak_api_client/api_client.py
keycloak_api_client/data_classes.py
keycloak_api_client/exceptions.py
keycloak_api_client/factories.py
python_keycloak_api_client-0.13.2.dist-info/LICENSE
python_keycloak_api_client-0.13.2.dist-info/METADATA
python_keycloak_api_client-0.13.2.dist-info/WHEEL
python_keycloak_api_client-0.13.2.dist-info/top_level.txt
python_keycloak_api_client-0.13.2.dist-info/RECORD
