Metadata-Version: 2.1
Name: python-keycloak-api-client
Version: 0.13.2
Summary: Client for Keycloak Api (mostly users and impersonation)
Home-page: https://github.com/masterplandev/python-keycloak-api-client
Author: Szymon Marcinkowski
Author-email: szymon@masterhub.com
License: MIT
Keywords: keycloak,client,api
Platform: UNKNOWN
Classifier: Environment :: Web Environment
Classifier: Intended Audience :: Developers
Classifier: License :: OSI Approved :: MIT License
Classifier: Operating System :: OS Independent
Classifier: Programming Language :: Python
Requires-Dist: attrs (>=19.3)
Requires-Dist: requests (>=2.23)
Provides-Extra: dev
Requires-Dist: pytest (>=6.2) ; extra == 'dev'
Requires-Dist: ruff (>=0.7.0) ; extra == 'dev'
Requires-Dist: pytest-vcr (>=1.0.2) ; extra == 'dev'
